resources/__init__.py
resources/accounting.py
resources/actions.py
resources/annexes.py
resources/areas.py
resources/auth.py
resources/banks.py
resources/billing.py
resources/celery_tasks.py
resources/clients.py
resources/contacts.py
resources/contracts.py
resources/costs.py
resources/countries.py
resources/currencies.py
resources/customfields.py
resources/defaults.py
resources/documents.py
resources/emails.py
resources/employees.py
resources/expenses.py
resources/fees.py
resources/files.py
resources/goals.py
resources/help.py
resources/helper.py
resources/imports.py
resources/inbound_emails.py
resources/indicators.py
resources/invitations.py
resources/invoices.py
resources/jobs.py
resources/languages.py
resources/lots.py
resources/milestones.py
resources/newsletters.py
resources/notes.py
resources/notifications.py
resources/ooti.py
resources/organizations.py
resources/orgusers.py
resources/payments.py
resources/permissions.py
resources/phases.py
resources/pipelines.py
resources/plans.py
resources/posts.py
resources/prescriptions.py
resources/profiles.py
resources/projections.py
resources/projects.py
resources/quickbooks.py
resources/reports.py
resources/revenue.py
resources/revisions.py
resources/roles.py
resources/stats.py
resources/styleguides.py
resources/tags.py
resources/tasks.py
resources/teams.py
resources/timelogs.py
resources/timeperiods.py
resources/token_auth.py
resources/token_refresh.py
resources/token_verify.py
resources/trips.py
resources/zones.py
ooti_api-1.0.3.dist-info/METADATA
ooti_api-1.0.3.dist-info/WHEEL
ooti_api-1.0.3.dist-info/top_level.txt
ooti_api-1.0.3.dist-info/RECORD
