Metadata-Version: 2.1
Name: ooti-api
Version: 1.0.3
Summary: SDK for ooti
Home-page: https://github.com/axonepro/sdk-ooti
Author: Axonepro
Author-email: accounts@ooti.co
License: UNKNOWN
Platform: UNKNOWN
Classifier: Programming Language :: Python
Classifier: Natural Language :: French
Classifier: Operating System :: OS Independent
Classifier: Programming Language :: Python :: 3.7
